Metadata-Version: 2.1
Name: dino-terminal
Version: 1.0.1
Summary: Chrome Dino game in your terminal
Home-page: https://github.com/busayojee/games/tree/master/dino-terminal
Author: Alabi Busayo
Author-email: busayo_jee@yahoo.com
Classifier: Environment :: Console :: Curses
Classifier: Natural Language :: English
Classifier: Operating System :: MacOS :: MacOS X
Classifier: Operating System :: POSIX
Classifier: Operating System :: Unix
Classifier: Programming Language :: Python :: 3
Classifier: Topic :: Utilities
Requires-Dist: curses-menu>=0.7.1
Requires-Dist: click==8.1.7
